{
    "Puzzles": [
        {
           "id":"1",
           "blunderMove":"f2",
           "fen":"8/8/4p3/3pP3/3P4/5p2/1R1K4/5bk1 b - - 9 64",
           "solution":[
              "Rb1",
              "Kg2",
              "Ke3",
              "Bd3",
              "Rb2",
              "Bf5",
              "Rxf2+"
           ],
           "orientation":"b"
        },
        {
           "id":"2",
           "blunderMove":"Ka7",
           "fen":"r1bq1b1r/6pp/pk3n2/3p4/5B2/1NQp4/PP3PPP/2R1R1K1 b - - 1 20",
           "solution":[
              "Na5"
           ],
           "orientation":"b"
        },
        {
           "id":"3",
           "blunderMove":"Qxd5",
           "fen":"r5k1/ppp2rp1/3p3p/3P2q1/3N1p2/3Q4/PPP5/1K4RR b - - 3 26",
           "solution":[
              "Rxh6",
              "Kf8",
              "Rh8+"
           ],
           "orientation":"b"
        },
        {
           "id":"4",
           "blunderMove":"Bd7",
           "fen":"rnbqkb1r/ppp1pppp/5n2/8/8/2N1BQ2/PPP3PP/3RKBNR b Kkq - 3 7",
           "solution":[
              "Qxb7"
           ],
           "orientation":"b"
        },
        {
           "blunderMove":"Bd6",
           "fen":"2r5/6k1/p1q2p2/1p1b2pp/2rPp3/Q1P1P1BP/5PP1/1RR3K1 w - - 2 33",
           "solution":[
              "Ra4",
              "Qc5",
              "Qb7"
           ],
           "orientation":"w",
           "id":"557b234ae13823b8379035b0"
        },
        {
            "blunderMove": "Qxa7",
            "elo": 1662,
            "fen": "2kr2r1/ppqn1p2/2p1pn1p/6p1/P3P1P1/1B2QNPP/1PP2K2/R6R w - - 1 22",
            "solution": [
                "Nxe4+",
                "Ke3",
                "Qxg3"
            ],
            "orientation":"w",
            "id": "557cae71e13823b81fb12e6b"
        },
        {
            "blunderMove": "Rhf8",
            "elo": 1231,
            "fen": "r6r/8/5R1p/4p3/kP1p2PP/P1pB1P2/K1P5/8 b - - 0 43",
            "solution": [
                "Rb6"
            ],
            "id": "55801ccde13823b81fb1abd2",
            "orientation": "b"
        }
     ]
}